{
  "classes": {
    "1": {
      "packageName": "com.ankamagames.dofus.datacenter.guild",
      "packageClass": "GuildRank",
      "fields": [
        {
          "name": "id",
          "type": "Integer"
        },
        {
          "name": "nameId",
          "type": "I18n"
        },
        {
          "name": "order",
          "type": "Integer"
        },
        {
          "name": "isModifiable",
          "type": "Boolean"
        },
        {
          "name": "gfxId",
          "type": "Integer"
        }
      ]
    }
  },
  "objects": [
    {
      "ClassType_": "GuildRank",
      "gfxId": 116,
      "id": 1,
      "isModifiable": false,
      "nameId": 932516,
      "order": 0
    },
    {
      "ClassType_": "GuildRank",
      "gfxId": 115,
      "id": 2,
      "isModifiable": true,
      "nameId": 932518,
      "order": 1
    },
    {
      "ClassType_": "GuildRank",
      "gfxId": 114,
      "id": 3,
      "isModifiable": true,
      "nameId": 932520,
      "order": 2
    },
    {
      "ClassType_": "GuildRank",
      "gfxId": 117,
      "id": 4,
      "isModifiable": false,
      "nameId": 932522,
      "order": 3
    }
  ]
}